railyard/__init__.py
railyard/assembler.py
railyard/builder.py
railyard/cli.py
railyard/railyard.py
railyard/tools.py
railyard_builder-0.1.1.dist-info/AUTHORS.rst
railyard_builder-0.1.1.dist-info/LICENSE
railyard_builder-0.1.1.dist-info/METADATA
railyard_builder-0.1.1.dist-info/WHEEL
railyard_builder-0.1.1.dist-info/entry_points.txt
railyard_builder-0.1.1.dist-info/top_level.txt
railyard_builder-0.1.1.dist-info/RECORD
