Metadata-Version: 2.1
Name: railyard-builder
Version: 0.1.1
Summary: Modular Jupyter Notebook container builds from Yaml definitions
Home-page: https://github.com/ktaletsk/railyard
Author: Konstantin Taletskiy
Author-email: konstantin@taletskiy.com
License: MIT license
Keywords: railyard
Platform: UNKNOWN
Classifier: Development Status :: 2 - Pre-Alpha
Classifier: Intended Audience :: Developers
Classifier: License :: OSI Approved :: MIT License
Classifier: Natural Language :: English
Classifier: Programming Language :: Python :: 3
Classifier: Programming Language :: Python :: 3.5
Classifier: Programming Language :: Python :: 3.6
Classifier: Programming Language :: Python :: 3.7
Classifier: Programming Language :: Python :: 3.8
Requires-Python: >=3.5
Requires-Dist: Click (>=7.0)
Requires-Dist: pyyaml
Requires-Dist: docker
